Gtk20Jiaocheng/README.md
Gtk20Jiaocheng/__init__.py
Gtk20Jiaocheng/__main__.py
Gtk20Jiaocheng/file.epub
Gtk20Jiaocheng/index.html
Gtk20Jiaocheng/css/__init__.py
Gtk20Jiaocheng/css/annotations.css
Gtk20Jiaocheng/css/main.css
Gtk20Jiaocheng/css/normalize.css
Gtk20Jiaocheng/css/popup.css
Gtk20Jiaocheng/font/__init__.py
Gtk20Jiaocheng/font/fontello.eot
Gtk20Jiaocheng/font/fontello.svg
Gtk20Jiaocheng/font/fontello.ttf
Gtk20Jiaocheng/font/fontello.woff
Gtk20Jiaocheng/img/__init__.py
Gtk20Jiaocheng/img/annotator-glyph-sprite.png
Gtk20Jiaocheng/img/annotator-icon-sprite.png
Gtk20Jiaocheng/img/apple-touch-icon.png
Gtk20Jiaocheng/img/cancelfullscreen.png
Gtk20Jiaocheng/img/close.png
Gtk20Jiaocheng/img/fullscreen.png
Gtk20Jiaocheng/img/loader.gif
Gtk20Jiaocheng/img/menu-icon.png
Gtk20Jiaocheng/img/save.png
Gtk20Jiaocheng/img/saved.png
Gtk20Jiaocheng/img/settings-s.png
Gtk20Jiaocheng/img/settings.png
Gtk20Jiaocheng/img/star.png
Gtk20Jiaocheng/js/__init__.py
Gtk20Jiaocheng/js/epub.js
Gtk20Jiaocheng/js/epub.min.js
Gtk20Jiaocheng/js/epub.min.map
Gtk20Jiaocheng/js/hooks.min.js
Gtk20Jiaocheng/js/hooks.min.map
Gtk20Jiaocheng/js/reader.js
Gtk20Jiaocheng/js/reader.js.map
Gtk20Jiaocheng/js/reader.min.js
Gtk20Jiaocheng/js/reader.min.map
Gtk20Jiaocheng/js/hooks/__init__.py
Gtk20Jiaocheng/js/hooks/extensions/__init__.py
Gtk20Jiaocheng/js/hooks/extensions/highlight.js
Gtk20Jiaocheng/js/libs/__init__.py
Gtk20Jiaocheng/js/libs/jquery.min.js
Gtk20Jiaocheng/js/libs/localforage.min.js
Gtk20Jiaocheng/js/libs/screenfull.js
Gtk20Jiaocheng/js/libs/screenfull.min.js
Gtk20Jiaocheng/js/libs/zip.min.js
Gtk20Jiaocheng/js/plugins/__init__.py
Gtk20Jiaocheng/js/plugins/hypothesis.js
Gtk20Jiaocheng/js/plugins/search.js
gtk_2_0_jiaocheng-2024.3.2.0.dist-info/METADATA
gtk_2_0_jiaocheng-2024.3.2.0.dist-info/WHEEL
gtk_2_0_jiaocheng-2024.3.2.0.dist-info/entry_points.txt
gtk_2_0_jiaocheng-2024.3.2.0.dist-info/top_level.txt
gtk_2_0_jiaocheng-2024.3.2.0.dist-info/RECORD
